{
  "query": "civic duty",
  "normalizedQuery": "civic duty",
  "contractVersion": "v1.7",
  "normalizerVersion": "2026-04-01.v2",
  "matcherVersion": "2026-04-01.v4",
  "conceptSetVersion": "20260401.2",
  "queryType": "unsupported_complex_query",
  "interpretation": {
    "interpretationType": "unsupported_complex",
    "message": "This query does not match a supported concept query form in the current runtime.",
    "concepts": [
      "duty"
    ]
  },
  "type": "no_exact_match",
  "resolution": {
    "method": "no_exact_match"
  },
  "message": "No exact canonical concept match was found for this query.",
  "suggestions": [
    {
      "conceptId": "duty",
      "title": "Duty",
      "reason": "broader_topic"
    }
  ]
}
